Workbook

Sheet калькуляция
A1: 1 | B1: Плановая калькуляция по расчету стоимости | D1: http://exceltable.com/
A2: № | B2: Статьи затрат | C2: Расчет показателя | D2: Сумма затрат на 1000 упаковок
A3: 2 | B3: Сырье и материалы | C3: "материалы" | D3: =материалы!F7 -> 0
A4: =A3+1 -> 3 | B4: Основная з/плата | C4: "осн.зарпл." | D4: =осн.зарпл.!E8 -> 0
A5: =A4+1 -> 4 | B5: Дополнительная з/плата | C5: 10% от ФОТ | D5: =D4*10% -> 0
A6: =A5+1 -> 5 | B6: Обязательные страховые взносы | C6: 30% от осн.и доп.з/п (22%+2,9%+5,1%) | D6: =(D4+D5)*30% -> 0
A7: =A6+1 -> 6 | B7: Амортизация ОС | C7: Бухгалтерский баланс
A8: =A7+1 -> 7 | B8: Полная себестоимость | C8: Расчетный показатель | D8: =D3+D4+D5+D6+D7 -> 0
A9: =A8+1 -> 8 | B9: Прибыль | C9: 0.3 | D9: =D8*30% -> 0
A10: =A9+1 -> 9 | B10: Цена без налогов | C10: Расчетный показатель | D10: =D8+D9 -> 0
A11: =A10+1 -> 10 | B11: Налоги | C11: 0.13 | D11: =D10*13% -> 0
A12: =A11+1 -> 11 | B12: Отпускная цена без НДС | C12: Расчетный показатель | D12: =D10+D11 -> 0
A13: =A12+1 -> 12 | B13: Цена 1 упаковки без НДС | C13: Расчетный показатель | D13: =D12/1000 -> 0

Sheet материалы
A1: 1 | B1: Стоимость материалов | F1: http://exceltable.com/
A2: № | B2: Наименование материала | C2: Ед.изм. | D2: Норма расхода | E2: Цена, руб. | F2: Стоимость, руб.
A3: 2 | B3: =нормы!C3 -> 0 | C3: =нормы!D3 -> 0 | D3: =нормы!G3 -> 0 | F3: =D3*E3 -> 0
A4: =A3+1 -> 3 | B4: =нормы!C4 -> 0 | C4: =нормы!D4 -> 0 | D4: =нормы!G4 -> 0 | F4: =D4*E4 -> 0
A5: =A4+1 -> 4 | B5: =нормы!C5 -> 0 | C5: =нормы!D5 -> 0 | D5: =нормы!G5 -> 0 | F5: =D5*E5 -> 0
A6: =A5+1 -> 5 | B6: =нормы!C6 -> 0 | C6: =нормы!D6 -> 0 | D6: =нормы!G6 -> 0 | F6: =D6*E6 -> 0
B7: Итого: | F7: =SUM(F3:F6) -> 0

Sheet нормы
A1: 1 | B1: Нормы расхода сырья на производство | F1: http://exceltable.com/
A2: № | B2: Деталь | C2: Наименование материала | D2: Ед.измер. | E2: Чистый расход | F2: Технологические потери,% | G2: Расход с учетом потерь
A3: 2 | G3: =E3+E3*F3 -> 0
A4: =A3+1 -> 3 | G4: =E4+E4*F4 -> 0
A5: =A4+1 -> 4 | G5: =E5+E5*F5 -> 0
A6: =A5+1 -> 5 | G6: =E6+E6*F6 -> 0

Sheet расценки
A1: 1 | B1: Пооперационные нормы времени и расценки | F1: http://exceltable.com/
A2: № | B2: Наименование операции | C2: Норма выработки, шт. | D2: Нормо-час | E2: Расценка, руб.
A3: 2 | E3: =C3*D3 -> 0
A4: =A3+1 -> 3 | E4: =C4*D4 -> 0
A5: =A4+1 -> 4 | E5: =C5*D5 -> 0
A6: =A5+1 -> 5 | E6: =C6*D6 -> 0
A7: =A6+1 -> 6 | E7: =C7*D7 -> 0

Sheet осн.зарпл.
A1: 1 | B1: Основная заработная плата производственных рабочих | F1: http://exceltable.com/
A2: № | B2: Наименование работ | C2: Расценка, руб. | D2: Премия, 30% | E2: Основная зарплата, руб.
A3: 2 | B3: =расценки!B3 -> 0 | C3: =расценки!E3 -> 0 | D3: =C3*30% -> 0 | E3: =C3+D3 -> 0
A4: =A3+1 -> 3 | B4: =расценки!B4 -> 0 | C4: =расценки!E4 -> 0 | D4: =C4*30% -> 0 | E4: =C4+D4 -> 0
A5: =A4+1 -> 4 | B5: =расценки!B5 -> 0 | C5: =расценки!E5 -> 0 | D5: =C5*30% -> 0 | E5: =C5+D5 -> 0
A6: =A5+1 -> 5 | B6: =расценки!B6 -> 0 | C6: =расценки!E6 -> 0 | D6: =C6*30% -> 0 | E6: =C6+D6 -> 0
A7: =A6+1 -> 6 | B7: =расценки!B7 -> 0 | C7: =расценки!E7 -> 0 | D7: =C7*30% -> 0 | E7: =C7+D7 -> 0
B8: Итого: | E8: =SUM(E3:E7) -> 0
